TestUtilsVikas2/Utils_Test1.py
TestUtilsVikas2/Utils_Test2.py
TestUtilsVikas2/__init__.py
TestUtilsVikas2-0.0.3.dist-info/METADATA
TestUtilsVikas2-0.0.3.dist-info/WHEEL
TestUtilsVikas2-0.0.3.dist-info/top_level.txt
TestUtilsVikas2-0.0.3.dist-info/RECORD
