Metadata-Version: 2.1
Name: TestUtilsVikas2
Version: 0.0.3
Summary: Common Utilities
Home-page: https://github.com/AeroVikas/TestUtilsVikas2.git
Download-URL: https://github.com/AeroVikas/TestUtilsVikas2.git
Author: Vikas Goel
Author-email: vikas.aero@gmail.com
Maintainer: Vikas Goel
Maintainer-email: vikas.aero@gmail.com
License: MIT
Project-URL: Bug Tracker, https://github.com/pypa/sampleproject/issues
Keywords: Furuness,Login,login,terminal
Classifier: Intended Audience :: Developers
Classifier: License :: OSI Approved :: MIT License
Classifier: Operating System :: OS Independent
Classifier: Programming Language :: Python :: 3
Requires-Python: >=3.11.9
Requires-Dist: pynput==1.7.3
